{
  "Status": {
    "Module": 0,
    "DeviceName": "NSPanel",
    "FriendlyName": [
      "NSPanel",
      ""
    ],
    "Topic": "nspanel_0CB4D0",
    "ButtonTopic": "0",
    "Power": 0,
    "PowerOnState": 3,
    "LedState": 1,
    "LedMask": "FFFF",
    "SaveData": 0,
    "SaveState": 1,
    "SwitchTopic": "0",
    "SwitchMode": [
      0,
      0,
      0,
      0,
      0,
      0,
      0,
      0,
      0,
      0,
      0,
      0,
      0,
      0,
      0,
      0,
      0,
      0,
      0,
      0,
      0,
      0,
      0,
      0,
      0,
      0,
      0,
      0
    ],
    "ButtonRetain": 0,
    "SwitchRetain": 0,
    "SensorRetain": 0,
    "PowerRetain": 0,
    "InfoRetain": 0,
    "StateRetain": 0,
    "StatusRetain": 0
  }
}